<?xml version="1.0" encoding="utf-8" standalone="yes" ?>
<T3locallang>
	<meta type="array">
		<type>module</type>
		<description>Language labels for plugin "PageStatistics" action "LastUpdated"</description>
	</meta>
	<data type="array">
		<languageKey index="default" type="array">
			<label index="flexform.title">settings</label>
			<label index="flexform.settings.storagePid">starting point</label>
			<label index="flexform.settings.offset">begin with entry #</label>
			<label index="flexform.settings.limit">amount of entries</label>
			<label index="flexform.settings.templateVariant">template variant</label>
			<label index="flexform.settings.templateVariant.heroUnit">hero unit</label>
			<label index="flexform.settings.templateVariant.minorUnit">minor unit</label>
		</languageKey>
		<languageKey index="de" type="array">
			<label index="flexform.title">Einstellungen</label>
			<label index="flexform.settings.storagePid">Ausgangspunkt</label>
			<label index="flexform.settings.offset">Beginne mit Eintrag Nummer</label>
			<label index="flexform.settings.limit">Anzahl Einträge</label>
			<label index="flexform.settings.templateVariant">Templatevariante</label>
			<label index="flexform.settings.templateVariant.heroUnit">Aufreißer</label>
			<label index="flexform.settings.templateVariant.minorUnit">zurückhaltender Teaser</label>
		</languageKey>
	</data>
</T3locallang>